plottwist/__init__.py
plottwist/plottwist.py
plottwist_py-1.0.1.dist-info/licenses/LICENSE
plottwist_py-1.0.1.dist-info/METADATA
plottwist_py-1.0.1.dist-info/WHEEL
plottwist_py-1.0.1.dist-info/top_level.txt
plottwist_py-1.0.1.dist-info/RECORD
