Metadata-Version: 2.4
Name: plottwist-py
Version: 1.0.1
Summary: plottwist makes plots reproducible from their PDFs.
Home-page: https://github.com/unkaktus/plottwist
Author: Ivan Markin
Author-email: git@unkaktus.art
License: MIT
Classifier: Programming Language :: Python :: 3
Classifier: License :: OSI Approved :: MIT License
Classifier: Operating System :: OS Independent
Requires-Python: >=3.7
License-File: LICENSE
Requires-Dist: matplotlib
Requires-Dist: msgpack
Dynamic: license-file
